{
  "users": [
    {
      "username": "abderrahim",
      "id": 1
    },
    {
      "username": "abderrahim",
      "id": 2
    },
    {
      "username": "abdderahim",
      "id": 3
    },
    {
      "username": "kllklklklg",
      "id": 4
    },
    {
      "username": "kidefghijklm",
      "id": 5
    },
    {
      "username": "abderrahim",
      "id": 6
    },
    {
      "username": "abderrahim",
      "id": 7
    },
    {
      "username": "abderrahim",
      "id": 8
    },
    {
      "username": "abderrahim",
      "id": 9
    },
    {
      "username": "abderrahim",
      "id": 10
    },
    {
      "username": "abderrahim",
      "id": 11
    },
    {
      "username": "abderrahim",
      "id": 12
    },
    {
      "username": "abderrahim",
      "id": 13
    },
    {
      "username": "abderrahim",
      "id": 14
    },
    {
      "username": "abderrahim",
      "id": 15
    },
    {
      "username": "abderrahim",
      "id": 16
    },
    {
      "username": "abderrahim",
      "id": 17
    },
    {
      "username": "abderrahim",
      "id": 18
    },
    {
      "username": "abderrahim",
      "id": 19
    },
    {
      "username": "abderrahim",
      "id": 20
    },
    {
      "username": "abderrahim",
      "id": 21
    },
    {
      "username": "abderrahim",
      "id": 22
    },
    {
      "username": "abderrahim",
      "id": 23
    },
    {
      "username": "abderrahim",
      "id": 24
    },
    {
      "username": "abderrahim",
      "id": 25
    },
    {
      "username": "abderrahim",
      "id": 26
    },
    {
      "username": "abderrahim",
      "id": 27
    },
    {
      "username": "abderrahim",
      "id": 28
    },
    {
      "username": "abderrahim",
      "id": 29
    },
    {
      "username": "abderrahim",
      "id": 30
    },
    {
      "username": "abderrahim",
      "id": 31
    },
    {
      "username": "abderrahim",
      "id": 32
    },
    {
      "username": "abderrahim",
      "id": 33
    },
    {
      "username": "abderrahim",
      "id": 34
    },
    {
      "username": "abderrahim",
      "id": 35
    },
    {
      "username": "abderrahim",
      "id": 36
    },
    {
      "username": "abderrahim",
      "id": 37
    },
    {
      "username": "abderrahim",
      "id": 38
    },
    {
      "username": "abderrahim",
      "id": 39
    },
    {
      "username": "abderrahim",
      "id": 40
    },
    {
      "username": "abderrahim",
      "id": 41
    },
    {
      "username": "abderrahim",
      "id": 42
    },
    {
      "username": "abderrahim",
      "id": 43
    },
    {
      "username": "abderrahim",
      "id": 44
    },
    {
      "username": "abderrahim",
      "id": 45
    },
    {
      "username": "abderrahim",
      "id": 46
    },
    {
      "username": "abderrahim",
      "id": 47
    },
    {
      "username": "abderrahim",
      "id": 48
    },
    {
      "username": "abderrahim",
      "id": 49
    },
    {
      "username": "abderrahim",
      "id": 50
    },
    {
      "username": "abderrahim",
      "id": 51
    },
    {
      "username": "abderrahim",
      "id": 52
    },
    {
      "username": "abderrahim",
      "id": 53
    },
    {
      "username": "abderrahim",
      "id": 54
    },
    {
      "username": "abderrahim",
      "id": 55
    },
    {
      "username": "abderrahim",
      "id": 56
    },
    {
      "username": "abderrahim",
      "id": 57
    },
    {
      "username": "abderrahim",
      "id": 58
    },
    {
      "username": "abderrahim",
      "id": 59
    },
    {
      "username": "abderrahim",
      "id": 60
    },
    {
      "username": "abderrahim",
      "id": 61
    },
    {
      "username": "abderrahim",
      "id": 62
    },
    {
      "username": "abderrahim",
      "id": 63
    },
    {
      "username": "abderrahim",
      "id": 64
    },
    {
      "username": "rvfbgfb",
      "id": 65
    },
    {
      "username": "abderrahim",
      "id": 66
    },
    {
      "username": "abderrahim",
      "id": 67
    },
    {
      "username": "abderrahim",
      "id": 68
    },
    {
      "username": "abderrahim",
      "id": 69
    },
    {
      "username": "abderrahim",
      "id": 70
    },
    {
      "username": "abderrahim",
      "id": 71
    },
    {
      "username": "abderrahim",
      "id": 72
    },
    {
      "username": "abderrahim",
      "id": 73
    },
    {
      "username": "abderrahim",
      "id": 74
    },
    {
      "username": "abderrahim",
      "id": 75
    },
    {
      "username": "abderrahim",
      "id": 76
    },
    {
      "username": "abderrahim",
      "id": 77
    },
    {
      "username": "abderrahim",
      "id": 78
    },
    {
      "username": "abderrahim",
      "id": 79
    },
    {
      "username": "abderrahim",
      "id": 80
    },
    {
      "username": "abderrahim",
      "id": 81
    },
    {
      "username": "abderrahim",
      "id": 82
    },
    {
      "username": "abderrahim",
      "id": 83
    },
    {
      "username": "kenza",
      "id": 84
    },
    {
      "username": "abderrahim",
      "id": 85
    },
    {
      "username": "abderrahim",
      "id": 86
    },
    {
      "username": "abderrahim",
      "id": 87
    },
    {
      "username": "abderrahim",
      "id": 88
    },
    {
      "username": "abderrahim",
      "id": 89
    },
    {
      "username": "abderrahim",
      "id": 90
    },
    {
      "username": "abderrahim",
      "id": 91
    },
    {
      "username": "abderrahim",
      "id": 92
    },
    {
      "username": "abderrahim",
      "id": 93
    },
    {
      "username": "abderrahim",
      "id": 94
    },
    {
      "username": "abderrahim",
      "id": 95
    },
    {
      "username": "abderrahim",
      "id": 96
    },
    {
      "username": "abderrahim",
      "id": 97
    },
    {
      "username": "abderrahim",
      "id": 98
    },
    {
      "username": "kenza",
      "id": 99
    },
    {
      "username": "abderrahim",
      "id": 100
    },
    {
      "username": "hakim",
      "id": 101
    },
    {
      "username": "abderrahim",
      "id": 102
    },
    {
      "username": "djamel",
      "id": 103
    },
    {
      "username": "abderrahim",
      "id": 104
    },
    {
      "username": "hola",
      "id": 105
    },
    {
      "username": "calvin",
      "id": 106
    },
    {
      "username": ",nb,b,,n,n,",
      "id": 107
    },
    {
      "username": "rahim",
      "id": 108
    },
    {
      "username": "rfgfrdg",
      "id": 109
    },
    {
      "username": "fhfhfh",
      "id": 110
    },
    {
      "username": "rahim",
      "id": 111
    },
    {
      "username": "rahim",
      "id": 112
    },
    {
      "username": "rahim",
      "id": 113
    },
    {
      "username": "rahim",
      "id": 114
    },
    {
      "username": "rahim",
      "id": 115
    },
    {
      "username": "rahim",
      "id": 116
    },
    {
      "username": "rahim",
      "id": 117
    },
    {
      "username": "rahim",
      "id": 118
    },
    {
      "username": "rahim",
      "id": 119
    },
    {
      "username": "rahim",
      "id": 120
    },
    {
      "username": "rahim",
      "id": 121
    },
    {
      "username": "rfdgf",
      "id": 122
    },
    {
      "username": "hgh",
      "id": 123
    },
    {
      "username": "rahim",
      "id": 124
    },
    {
      "username": "rahim",
      "id": 125
    },
    {
      "username": "abderrahim",
      "id": 126
    },
    {
      "username": "rahim",
      "id": 127
    },
    {
      "username": "rahim",
      "id": 128
    },
    {
      "username": "rahim",
      "id": 129
    },
    {
      "username": "rahim",
      "id": 130
    },
    {
      "username": "rahim",
      "id": 131
    },
    {
      "username": "rahim",
      "id": 132
    },
    {
      "username": "rahim",
      "id": 133
    },
    {
      "username": "rahim",
      "id": 134
    },
    {
      "username": "rahim",
      "id": 135
    },
    {
      "username": "rahim",
      "id": 136
    },
    {
      "username": "rahim",
      "id": 137
    }
  ],
  "messages": [
    {
      "content": "bonjour",
      "authorId": "abderrahim",
      "threadId": "1",
      "date": "2023-12-01T15:10:50.993Z",
      "id": 1
    },
    {
      "content": "comment vous allez",
      "authorId": "rahim",
      "threadId": "1",
      "date": "2023-12-01T15:16:06.281Z",
      "id": 2
    },
    {
      "content": "je vais bien merci",
      "authorId": "rahim",
      "threadId": "1",
      "date": "2023-12-01T15:16:15.537Z",
      "id": 3
    },
    {
      "content": "bonjour tout le monde",
      "authorId": "rahim",
      "threadId": "3",
      "date": "2023-12-01T15:18:38.873Z",
      "id": 4
    },
    {
      "content": "j'aime bien la musique ",
      "authorId": "rahim",
      "threadId": "3",
      "date": "2023-12-01T15:18:51.921Z",
      "id": 5
    }
  ],
  "threads": [
    {
      "id": "1",
      "label": "Discussion Générale"
    },
    {
      "id": "2",
      "label": "Projets"
    },
    {
      "id": "3",
      "label": "foot"
    },
    {
      "id": "4",
      "label": "musiques"
    }
  ]
}